{
  "version": "1.1.1",
  "windows": {
    "main": {
      "main": true,
      "url": "app://editor/index.html",
      "windowType": "dockable",
      "x": 1440,
      "y": -82,
      "width": 1920,
      "height": 1080,
      "layout": {
        "children": [
          {
            "children": [
              {
                "active": 0,
                "children": [
                  "hierarchy"
                ],
                "height": 649,
                "type": "panel",
                "width": 304
              },
              {
                "active": 0,
                "children": [
                  "assets"
                ],
                "height": 369,
                "type": "panel",
                "width": 304
              }
            ],
            "height": 1021,
            "type": "dock-v",
            "width": 304
          },
          {
            "children": [
              {
                "active": 0,
                "children": [
                  "scene"
                ],
                "height": 570,
                "type": "panel",
                "width": 1204
              },
              {
                "active": 1,
                "children": [
                  "console",
                  "timeline",
                  "game-window"
                ],
                "height": 448,
                "type": "panel",
                "width": 1204
              }
            ],
            "height": 1021,
            "type": "dock-v",
            "width": 1204
          },
          {
            "active": 0,
            "children": [
              "inspector",
              "cocos-services"
            ],
            "height": 1021,
            "type": "panel",
            "width": 406
          }
        ],
        "type": "dock-h"
      },
      "panels": [
        "hierarchy",
        "assets",
        "scene",
        "console",
        "timeline",
        "game-window",
        "inspector",
        "cocos-services"
      ]
    }
  },
  "panels": {
    "preferences": {
      "x": 634,
      "y": 226,
      "width": 584,
      "height": 548
    },
    "project-settings": {
      "x": 1727,
      "y": 122,
      "width": 584,
      "height": 548
    },
    "sprite-editor": {
      "x": 710,
      "y": 267,
      "width": 500,
      "height": 522
    },
    "builder": {
      "x": 698,
      "y": 33,
      "width": 654,
      "height": 722
    }
  },
  "panelLabelWidth": {
    "inspector": null,
    "builder": null
  },
  "panelLabelWidth.inspector": null,
  "panelLabelWidth.builder": null
}
